LICENSE
README.md
setup.py
alienX/__init__.py
alienX.egg-info/PKG-INFO
alienX.egg-info/SOURCES.txt
alienX.egg-info/dependency_links.txt
alienX.egg-info/top_level.txt