Metadata-Version: 2.1
Name: alienX
Version: 0.1.0
Summary: soon
Home-page: https://github.com/ishanoshada/alinex
Author: Ishan Oshada
Author-email: ic31908@gamil.com
License: MIT
Platform: UNKNOWN
